{
    "Airliner": {
        "apps": {
            "VC": {
                "operations": {
                  "Noop":           { "airliner_mid": "0x1c3b" },
                  "Reset":          { "airliner_mid": "0x1c3b" },
                  "StartStreaming": { "airliner_mid": "0x1c3b" },
                  "StopStreaming":  { "airliner_mid": "0x1c3b" },
                  "VC_HkTlm_t":     { "airliner_mid": "0x0c39" },
                  "Wakeup":         { "airliner_mid": "0x1c3c" },
                  "SendHk":         { "airliner_mid": "0x1c3a" }
                },
                "config": {
                }
            }
        }
    }
}
